template_pypackage_builder/__init__.py
template_pypackage_builder/__pycache__/test.cpython-310.pyc
template_pypackage_builder/types/Apache Version 2.0.txt
template_pypackage_builder/types/GNU GPLv3.txt
template_pypackage_builder/types/MIT License.txt
template_pypackage_builder/types/Mozilla Public License 2.0.txt
template_pypackage_builder/types/The Unlicense.txt
template_pypackage_builder/types/user_defined.txt
template_pypackage_builder-0.9.dist-info/METADATA
template_pypackage_builder-0.9.dist-info/WHEEL
template_pypackage_builder-0.9.dist-info/entry_points.txt
template_pypackage_builder-0.9.dist-info/top_level.txt
template_pypackage_builder-0.9.dist-info/RECORD
