Metadata-Version: 2.1
Name: template-pypackage-builder
Version: 0.9
Summary: A simple tool for packaging python
Home-page: https://github.com/dipson94/packagemaker
Author: Dipson
Classifier: License :: OSI Approved :: GNU General Public License v3 (GPLv3)
Classifier: Programming Language :: Python :: 3.10
Classifier: Operating System :: OS Independent
Requires-Python: >=3.10
Requires-Dist: pyperclip
